CHANGELOG.md
README.md
agentpluginapi/__init__.py
agentpluginapi/agent_binary_request.py
agentpluginapi/dropper_execution_mode.py
agentpluginapi/exploiter_result.py
agentpluginapi/fingerprint_data.py
agentpluginapi/i_agent_binary_repository.py
agentpluginapi/i_agent_command_builder_factory.py
agentpluginapi/i_agent_event_publishler.py
agentpluginapi/i_agent_otp_provider.py
agentpluginapi/i_http_agent_binary_server_registrar.py
agentpluginapi/i_linux_agent_command_builder.py
agentpluginapi/i_propagation_credentials_repository.py
agentpluginapi/i_tcp_port_selector.py
agentpluginapi/i_windows_agent_command_builder.py
agentpluginapi/local_machine_info.py
agentpluginapi/payload_result.py
agentpluginapi/ping_scan_data.py
agentpluginapi/port_scan_data.py
agentpluginapi/py.typed
agentpluginapi/target_host.py
monkey_agentpluginapi-0.11.0.dist-info/LICENSE
monkey_agentpluginapi-0.11.0.dist-info/METADATA
monkey_agentpluginapi-0.11.0.dist-info/WHEEL
monkey_agentpluginapi-0.11.0.dist-info/RECORD
